lando_util/__init__.py
lando_util/stagedata.py
lando_util/upload.py
lando_util/organize_project/__init__.py
lando_util/organize_project/__main__.py
lando_util/organize_project/organizer.py
lando_util/organize_project/reports.py
lando_util-0.5.4.dist-info/LICENSE
lando_util-0.5.4.dist-info/METADATA
lando_util-0.5.4.dist-info/WHEEL
lando_util-0.5.4.dist-info/top_level.txt
lando_util-0.5.4.dist-info/RECORD
