Metadata-Version: 2.1
Name: lando-util
Version: 0.5.4
Summary: Utility functions for https://github.com/Duke-GCB/lando
Home-page: http://github.com/Duke-GCB/lando-util
Author: UNKNOWN
Author-email: UNKNOWN
License: MIT
Platform: UNKNOWN
Requires-Dist: click (==7.0)
Requires-Dist: Jinja2 (==2.10.1)
Requires-Dist: DukeDSClient (==2.2.0)
Requires-Dist: humanfriendly (==2.4)
Requires-Dist: python-dateutil (==2.6.0)
Requires-Dist: Markdown (==2.6.9)
Requires-Dist: PyYAML (==5.1)
